test_subprocess.py
bumpline/cli.py
bumpline/separate_version.py
bumpline/version.py
bumpline-0.5.dist-info/METADATA
bumpline-0.5.dist-info/WHEEL
bumpline-0.5.dist-info/entry_points.txt
bumpline-0.5.dist-info/licenses/LICENSE
bumpline-0.5.dist-info/RECORD
