Metadata-Version: 2.1
Name: bumpline
Version: 0.5
Summary: Manage your python project more easily
Project-URL: Homepage, https://github.com/llucasls/bumpline
Author-email: "Lucas L. S. Haine" <lucaslshaine@gmail.com>
License-File: LICENSE
Classifier: License :: OSI Approved :: MIT License
Classifier: Operating System :: POSIX
Classifier: Programming Language :: Python :: 3
Requires-Python: >=3.7
Requires-Dist: toml
